avat/__init__.py
avat/api_request.py
avat/personas.py
avat/utils.py
avat-0.3.6.dist-info/LICENSE
avat-0.3.6.dist-info/METADATA
avat-0.3.6.dist-info/WHEEL
avat-0.3.6.dist-info/top_level.txt
avat-0.3.6.dist-info/RECORD
