Metadata-Version: 2.2
Name: avat
Version: 0.3.6
Summary: AI personas
Author-email: lorepieri <lorepieri@hotmail.it>
Classifier: Programming Language :: Python :: 3
Classifier: Operating System :: OS Independent
Requires-Python: >=3.8
License-File: LICENSE
Requires-Dist: icecream==2.1
